pynf/__init__.py
pynf/cli.py
pynf/engine.py
pynf/input_validation.py
pynf/nfcore.py
pynf/result.py
pynf/tools.py
pynf_agent/__init__.py
pynf_agent/agent.py
pynf_agent/cli.py
pynf_agent/openrouter_client.py
pynf_agent/tools.py
nfpy-0.1.0.dist-info/METADATA
nfpy-0.1.0.dist-info/WHEEL
nfpy-0.1.0.dist-info/entry_points.txt
nfpy-0.1.0.dist-info/RECORD
