Metadata-Version: 2.4
Name: nfpy
Version: 0.1.0
Summary: Add your description here
Requires-Python: >=3.12
Requires-Dist: click>=8.1.0
Requires-Dist: jpype1>=1.6.0
Requires-Dist: litellm>=1.79.0
Requires-Dist: pytest>=8.4.2
Requires-Dist: python-dotenv>=1.1.1
Requires-Dist: pyyaml>=6.0
Requires-Dist: requests>=2.32.5
Requires-Dist: rich>=13.0.0
Requires-Dist: smolagents>=1.22.0
Provides-Extra: agent
Requires-Dist: duckduckgo-search; extra == 'agent'
Requires-Dist: openai>=1.0.0; extra == 'agent'
Requires-Dist: smolagents; extra == 'agent'
